ErisPulse/__init__.py
ErisPulse/__main__.py
ErisPulse/Core/__init__.py
ErisPulse/Core/_self_config.py
ErisPulse/Core/adapter.py
ErisPulse/Core/config.py
ErisPulse/Core/exceptions.py
ErisPulse/Core/lifecycle.py
ErisPulse/Core/logger.py
ErisPulse/Core/module.py
ErisPulse/Core/router.py
ErisPulse/Core/storage.py
ErisPulse/Core/ux.py
ErisPulse/Core/Bases/__init__.py
ErisPulse/Core/Bases/adapter.py
ErisPulse/Core/Bases/module.py
ErisPulse/Core/Event/__init__.py
ErisPulse/Core/Event/base.py
ErisPulse/Core/Event/command.py
ErisPulse/Core/Event/exceptions.py
ErisPulse/Core/Event/message.py
ErisPulse/Core/Event/meta.py
ErisPulse/Core/Event/notice.py
ErisPulse/Core/Event/request.py
ErisPulse/utils/__init__.py
ErisPulse/utils/cli.py
ErisPulse/utils/console.py
ErisPulse/utils/package_manager.py
ErisPulse/utils/reload_handler.py
erispulse-2.3.2.dist-info/METADATA
erispulse-2.3.2.dist-info/WHEEL
erispulse-2.3.2.dist-info/entry_points.txt
erispulse-2.3.2.dist-info/licenses/LICENSE
erispulse-2.3.2.dist-info/RECORD
