Metadata-Version: 2.4
Name: ErisPulse
Version: 2.3.2
Summary: ErisPulse 是一个模块化、可扩展的异步 Python SDK 框架，主要用于构建高效、可维护的机器人应用程序。
Author-email: "艾莉丝·格雷拉特(WSu2059)" <wsu2059@qq.com>
License: MIT License
License-File: LICENSE
Classifier: Development Status :: 5 - Production/Stable
Classifier: Intended Audience :: Developers
Classifier: License :: OSI Approved :: MIT License
Classifier: Operating System :: OS Independent
Classifier: Programming Language :: Python :: 3
Classifier: Programming Language :: Python :: 3 :: Only
Classifier: Programming Language :: Python :: 3.10
Classifier: Programming Language :: Python :: 3.11
Classifier: Programming Language :: Python :: 3.12
Classifier: Programming Language :: Python :: 3.13
Classifier: Topic :: Software Development :: Libraries :: Python Modules
Requires-Python: >=3.10
Requires-Dist: aiohttp
Requires-Dist: colorama
Requires-Dist: fastapi>=0.116.1
Requires-Dist: hypercorn>=0.14.0
Requires-Dist: keyboard
Requires-Dist: packaging>=25.0
Requires-Dist: pip
Requires-Dist: pydantic>=2.10.6
Requires-Dist: python-multipart>=0.0.20
Requires-Dist: rich
Requires-Dist: toml
Requires-Dist: watchdog
